codenerix_invoicing/__init__.py
codenerix_invoicing/admin.py
codenerix_invoicing/apps.py
codenerix_invoicing/exceptions.py
codenerix_invoicing/forms.py
codenerix_invoicing/forms_cash.py
codenerix_invoicing/forms_purchases.py
codenerix_invoicing/forms_reason.py
codenerix_invoicing/forms_sales.py
codenerix_invoicing/helpers.py
codenerix_invoicing/models.py
codenerix_invoicing/models_cash.py
codenerix_invoicing/models_purchases.py
codenerix_invoicing/models_sales.py
codenerix_invoicing/models_sales_original.py
codenerix_invoicing/models_sales_w_lines.py
codenerix_invoicing/settings.py
codenerix_invoicing/urls.py
codenerix_invoicing/urls_cash.py
codenerix_invoicing/urls_purchases.py
codenerix_invoicing/urls_sales.py
codenerix_invoicing/version.py
codenerix_invoicing/views.py
codenerix_invoicing/views_cash.py
codenerix_invoicing/views_purchases.py
codenerix_invoicing/views_reason.py
codenerix_invoicing/views_sales.py
codenerix_invoicing/locale/en/LC_MESSAGES/django.po
codenerix_invoicing/locale/es/LC_MESSAGES/django.mo
codenerix_invoicing/locale/es/LC_MESSAGES/django.po
codenerix_invoicing/migrations/0001_initial.py
codenerix_invoicing/migrations/0002_auto_20180129_0937.py
codenerix_invoicing/migrations/0003_auto_20180129_0941.py
codenerix_invoicing/migrations/0004_saleslines.py
codenerix_invoicing/migrations/0005_auto_20180129_1211.py
codenerix_invoicing/migrations/0006_auto_20180129_1256.py
codenerix_invoicing/migrations/0007_auto_20180129_1258.py
codenerix_invoicing/migrations/0008_auto_20180130_1312.py
codenerix_invoicing/migrations/0009_salesorderdocument.py
codenerix_invoicing/migrations/0010_reasonmodification.py
codenerix_invoicing/migrations/0011_reasonmodificationlinealbaran_reasonmodificationlinebasket_reasonmodificationlineinvoice_reasonmodif.py
codenerix_invoicing/migrations/0012_auto_20180201_1212.py
codenerix_invoicing/migrations/0013_salesorderdocument_removed.py
codenerix_invoicing/migrations/0014_auto_20180227_0858.py
django_codenerix_invoicing-4.0.2.dist-info/LICENSE
django_codenerix_invoicing-4.0.2.dist-info/METADATA
django_codenerix_invoicing-4.0.2.dist-info/WHEEL
django_codenerix_invoicing-4.0.2.dist-info/top_level.txt
django_codenerix_invoicing-4.0.2.dist-info/RECORD
