Metadata-Version: 2.1
Name: django-codenerix-invoicing
Version: 4.0.2
Summary: Codenerix Invoicing is a module that enables CODENERIX to manage bills.
Home-page: https://github.com/codenerix/django-codenerix-invoicing
Author: Juan Miguel Taboada Godoy <juanmi@juanmitaboada.com>, Juan Soler Ruiz <soleronline@gmail.com>
Author-email: UNKNOWN
License: Apache License Version 2.0
Keywords: django,codenerix,management,erp,crm,invoicing,sales,purchases,cash,cashdiary,diary
Platform: OS Independent
Classifier: Environment :: Web Environment
Classifier: Framework :: Django
Classifier: Framework :: Django :: 1.8
Classifier: Framework :: Django :: 1.9
Classifier: Framework :: Django :: 1.10
Classifier: Intended Audience :: Developers
Classifier: License :: Other/Proprietary License
Classifier: Operating System :: OS Independent
Classifier: Programming Language :: Python
Classifier: Programming Language :: Python :: 3.5
Classifier: Programming Language :: Python :: 3.6
Classifier: Programming Language :: Python :: 3.7
Classifier: Programming Language :: Python :: 3.8
Classifier: Programming Language :: Python :: 3.9
Classifier: Topic :: Internet :: WWW/HTTP
Classifier: Topic :: Internet :: WWW/HTTP :: Dynamic Content
Requires-Dist: django-codenerix
Requires-Dist: django-codenerix-extensions
Requires-Dist: django-codenerix-pos
Requires-Dist: django-codenerix-products
Requires-Dist: django-codenerix-storages
Requires-Dist: pyphen
Requires-Dist: xhtml2pdf
